{
  "scriptId": "263",
  "url": "file:///Users/m/dev/polyseam/cndi/src/outputs/terraform-node-resource.ts",
  "functions": [
    {
      "functionName": "",
      "ranges": [{ "startOffset": 0, "endOffset": 9137, "count": 1 }],
      "isBlockCoverage": true
    },
    {
      "functionName": "getTerraformNodeResource",
      "ranges": [{ "startOffset": 250, "endOffset": 759, "count": 0 }],
      "isBlockCoverage": false
    },
    {
      "functionName": "getGCPNodeResource",
      "ranges": [{ "startOffset": 788, "endOffset": 5067, "count": 0 }],
      "isBlockCoverage": false
    },
    {
      "functionName": "getAWSNodeResource",
      "ranges": [{ "startOffset": 5096, "endOffset": 9094, "count": 0 }],
      "isBlockCoverage": false
    }
  ]
}
